{"sections":[],"kind":"symbol","schemaVersion":{"major":0,"minor":3,"patch":0},"abstract":[{"type":"text","text":"The SRTPerformanceData represents the SRT’s performance statistics. This struct is wrapper for an CBytePerfMon."}],"topicSections":[{"title":"Instance Properties","generated":true,"identifiers":["doc:\/\/SRTHaishinKit\/documentation\/SRTHaishinKit\/SRTPerformanceData\/byteAvailRcvBuf","doc:\/\/SRTHaishinKit\/documentation\/SRTHaishinKit\/SRTPerformanceData\/byteAvailSndBuf","doc:\/\/SRTHaishinKit\/documentation\/SRTHaishinKit\/SRTPerformanceData\/byteMSS","doc:\/\/SRTHaishinKit\/documentation\/SRTHaishinKit\/SRTPerformanceData\/byteRcvBuf","doc:\/\/SRTHaishinKit\/documentation\/SRTHaishinKit\/SRTPerformanceData\/byteRcvDrop","doc:\/\/SRTHaishinKit\/documentation\/SRTHaishinKit\/SRTPerformanceData\/byteRcvDropTotal","doc:\/\/SRTHaishinKit\/documentation\/SRTHaishinKit\/SRTPerformanceData\/byteRcvLoss","doc:\/\/SRTHaishinKit\/documentation\/SRTHaishinKit\/SRTPerformanceData\/byteRcvLossTotal","doc:\/\/SRTHaishinKit\/documentation\/SRTHaishinKit\/SRTPerformanceData\/byteRcvUndecrypt","doc:\/\/SRTHaishinKit\/documentation\/SRTHaishinKit\/SRTPerformanceData\/byteRcvUndecryptTotal","doc:\/\/SRTHaishinKit\/documentation\/SRTHaishinKit\/SRTPerformanceData\/byteRecv","doc:\/\/SRTHaishinKit\/documentation\/SRTHaishinKit\/SRTPerformanceData\/byteRecvTotal","doc:\/\/SRTHaishinKit\/documentation\/SRTHaishinKit\/SRTPerformanceData\/byteRetrans","doc:\/\/SRTHaishinKit\/documentation\/SRTHaishinKit\/SRTPerformanceData\/byteRetransTotal","doc:\/\/SRTHaishinKit\/documentation\/SRTHaishinKit\/SRTPerformanceData\/byteSent","doc:\/\/SRTHaishinKit\/documentation\/SRTHaishinKit\/SRTPerformanceData\/byteSentTotal","doc:\/\/SRTHaishinKit\/documentation\/SRTHaishinKit\/SRTPerformanceData\/byteSndBuf","doc:\/\/SRTHaishinKit\/documentation\/SRTHaishinKit\/SRTPerformanceData\/byteSndDrop","doc:\/\/SRTHaishinKit\/documentation\/SRTHaishinKit\/SRTPerformanceData\/byteSndDropTotal","doc:\/\/SRTHaishinKit\/documentation\/SRTHaishinKit\/SRTPerformanceData\/mbpsBandwidth","doc:\/\/SRTHaishinKit\/documentation\/SRTHaishinKit\/SRTPerformanceData\/mbpsMaxBW","doc:\/\/SRTHaishinKit\/documentation\/SRTHaishinKit\/SRTPerformanceData\/mbpsRecvRate","doc:\/\/SRTHaishinKit\/documentation\/SRTHaishinKit\/SRTPerformanceData\/mbpsSendRate","doc:\/\/SRTHaishinKit\/documentation\/SRTHaishinKit\/SRTPerformanceData\/msRTT","doc:\/\/SRTHaishinKit\/documentation\/SRTHaishinKit\/SRTPerformanceData\/msRcvBuf","doc:\/\/SRTHaishinKit\/documentation\/SRTHaishinKit\/SRTPerformanceData\/msRcvTsbPdDelay","doc:\/\/SRTHaishinKit\/documentation\/SRTHaishinKit\/SRTPerformanceData\/msSndBuf","doc:\/\/SRTHaishinKit\/documentation\/SRTHaishinKit\/SRTPerformanceData\/msSndTsbPdDelay","doc:\/\/SRTHaishinKit\/documentation\/SRTHaishinKit\/SRTPerformanceData\/msTimeStamp","doc:\/\/SRTHaishinKit\/documentation\/SRTHaishinKit\/SRTPerformanceData\/pktCongestionWindow","doc:\/\/SRTHaishinKit\/documentation\/SRTHaishinKit\/SRTPerformanceData\/pktFlightSize","doc:\/\/SRTHaishinKit\/documentation\/SRTHaishinKit\/SRTPerformanceData\/pktFlowWindow","doc:\/\/SRTHaishinKit\/documentation\/SRTHaishinKit\/SRTPerformanceData\/pktRcvAvgBelatedTime","doc:\/\/SRTHaishinKit\/documentation\/SRTHaishinKit\/SRTPerformanceData\/pktRcvBelated","doc:\/\/SRTHaishinKit\/documentation\/SRTHaishinKit\/SRTPerformanceData\/pktRcvBuf","doc:\/\/SRTHaishinKit\/documentation\/SRTHaishinKit\/SRTPerformanceData\/pktRcvDrop","doc:\/\/SRTHaishinKit\/documentation\/SRTHaishinKit\/SRTPerformanceData\/pktRcvDropTotal","doc:\/\/SRTHaishinKit\/documentation\/SRTHaishinKit\/SRTPerformanceData\/pktRcvFilterExtra","doc:\/\/SRTHaishinKit\/documentation\/SRTHaishinKit\/SRTPerformanceData\/pktRcvFilterExtraTotal","doc:\/\/SRTHaishinKit\/documentation\/SRTHaishinKit\/SRTPerformanceData\/pktRcvFilterLoss","doc:\/\/SRTHaishinKit\/documentation\/SRTHaishinKit\/SRTPerformanceData\/pktRcvFilterLossTotal","doc:\/\/SRTHaishinKit\/documentation\/SRTHaishinKit\/SRTPerformanceData\/pktRcvFilterSupply","doc:\/\/SRTHaishinKit\/documentation\/SRTHaishinKit\/SRTPerformanceData\/pktRcvFilterSupplyTotal","doc:\/\/SRTHaishinKit\/documentation\/SRTHaishinKit\/SRTPerformanceData\/pktRcvLoss","doc:\/\/SRTHaishinKit\/documentation\/SRTHaishinKit\/SRTPerformanceData\/pktRcvLossTotal","doc:\/\/SRTHaishinKit\/documentation\/SRTHaishinKit\/SRTPerformanceData\/pktRcvRetrans","doc:\/\/SRTHaishinKit\/documentation\/SRTHaishinKit\/SRTPerformanceData\/pktRcvUndecrypt","doc:\/\/SRTHaishinKit\/documentation\/SRTHaishinKit\/SRTPerformanceData\/pktRcvUndecryptTotal","doc:\/\/SRTHaishinKit\/documentation\/SRTHaishinKit\/SRTPerformanceData\/pktRecv","doc:\/\/SRTHaishinKit\/documentation\/SRTHaishinKit\/SRTPerformanceData\/pktRecvACK","doc:\/\/SRTHaishinKit\/documentation\/SRTHaishinKit\/SRTPerformanceData\/pktRecvACKTotal","doc:\/\/SRTHaishinKit\/documentation\/SRTHaishinKit\/SRTPerformanceData\/pktRecvNAK","doc:\/\/SRTHaishinKit\/documentation\/SRTHaishinKit\/SRTPerformanceData\/pktRecvNAKTotal","doc:\/\/SRTHaishinKit\/documentation\/SRTHaishinKit\/SRTPerformanceData\/pktRecvTotal","doc:\/\/SRTHaishinKit\/documentation\/SRTHaishinKit\/SRTPerformanceData\/pktReorderDistance","doc:\/\/SRTHaishinKit\/documentation\/SRTHaishinKit\/SRTPerformanceData\/pktReorderTolerance","doc:\/\/SRTHaishinKit\/documentation\/SRTHaishinKit\/SRTPerformanceData\/pktRetrans","doc:\/\/SRTHaishinKit\/documentation\/SRTHaishinKit\/SRTPerformanceData\/pktRetransTotal","doc:\/\/SRTHaishinKit\/documentation\/SRTHaishinKit\/SRTPerformanceData\/pktSent","doc:\/\/SRTHaishinKit\/documentation\/SRTHaishinKit\/SRTPerformanceData\/pktSentACK","doc:\/\/SRTHaishinKit\/documentation\/SRTHaishinKit\/SRTPerformanceData\/pktSentACKTotal","doc:\/\/SRTHaishinKit\/documentation\/SRTHaishinKit\/SRTPerformanceData\/pktSentNAK","doc:\/\/SRTHaishinKit\/documentation\/SRTHaishinKit\/SRTPerformanceData\/pktSentNAKTotal","doc:\/\/SRTHaishinKit\/documentation\/SRTHaishinKit\/SRTPerformanceData\/pktSentTotal","doc:\/\/SRTHaishinKit\/documentation\/SRTHaishinKit\/SRTPerformanceData\/pktSndBuf","doc:\/\/SRTHaishinKit\/documentation\/SRTHaishinKit\/SRTPerformanceData\/pktSndDrop","doc:\/\/SRTHaishinKit\/documentation\/SRTHaishinKit\/SRTPerformanceData\/pktSndDropTotal","doc:\/\/SRTHaishinKit\/documentation\/SRTHaishinKit\/SRTPerformanceData\/pktSndFilterExtra","doc:\/\/SRTHaishinKit\/documentation\/SRTHaishinKit\/SRTPerformanceData\/pktSndFilterExtraTotal","doc:\/\/SRTHaishinKit\/documentation\/SRTHaishinKit\/SRTPerformanceData\/pktSndLoss","doc:\/\/SRTHaishinKit\/documentation\/SRTHaishinKit\/SRTPerformanceData\/pktSndLossTotal","doc:\/\/SRTHaishinKit\/documentation\/SRTHaishinKit\/SRTPerformanceData\/usPktSndPeriod","doc:\/\/SRTHaishinKit\/documentation\/SRTHaishinKit\/SRTPerformanceData\/usSndDuration","doc:\/\/SRTHaishinKit\/documentation\/SRTHaishinKit\/SRTPerformanceData\/usSndDurationTotal"],"anchor":"Instance-Properties"}],"primaryContentSections":[{"kind":"declarations","declarations":[{"languages":["swift"],"platforms":["macOS"],"tokens":[{"text":"struct","kind":"keyword"},{"text":" ","kind":"text"},{"text":"SRTPerformanceData","kind":"identifier"}]}]},{"kind":"content","content":[{"level":2,"type":"heading","text":"Overview","anchor":"overview"},{"name":"See Also","content":[{"type":"paragraph","inlineContent":[{"text":"https:\/\/github.com\/Haivision\/srt\/blob\/master\/srtcore\/srt.h","type":"text"}]}],"type":"aside","style":"note"}]}],"relationshipsSections":[{"kind":"relationships","title":"Conforms To","type":"conformsTo","identifiers":["doc:\/\/SRTHaishinKit\/s8SendableP"]}],"hierarchy":{"paths":[["doc:\/\/SRTHaishinKit\/documentation\/SRTHaishinKit"]]},"variants":[{"traits":[{"interfaceLanguage":"swift"}],"paths":["\/documentation\/srthaishinkit\/srtperformancedata"]}],"metadata":{"modules":[{"name":"SRTHaishinKit"}],"symbolKind":"struct","roleHeading":"Structure","role":"symbol","title":"SRTPerformanceData","fragments":[{"kind":"keyword","text":"struct"},{"kind":"text","text":" "},{"kind":"identifier","text":"SRTPerformanceData"}],"externalID":"s:13SRTHaishinKit18SRTPerformanceDataV","navigatorTitle":[{"text":"SRTPerformanceData","kind":"identifier"}]},"identifier":{"url":"doc:\/\/SRTHaishinKit\/documentation\/SRTHaishinKit\/SRTPerformanceData","interfaceLanguage":"swift"},"references":{"doc://SRTHaishinKit/documentation/SRTHaishinKit/SRTPerformanceData/byteSent":{"url":"\/documentation\/srthaishinkit\/srtperformancedata\/bytesent","role":"symbol","title":"byteSent","type":"topic","kind":"symbol","identifier":"doc:\/\/SRTHaishinKit\/documentation\/SRTHaishinKit\/SRTPerformanceData\/byteSent","abstract":[{"type":"text","text":"The number of sent data bytes, including retransmissions"}],"fragments":[{"text":"let","kind":"keyword"},{"text":" ","kind":"text"},{"text":"byteSent","kind":"identifier"},{"text":": ","kind":"text"},{"text":"UInt64","kind":"typeIdentifier","preciseIdentifier":"s:s6UInt64V"}]},"doc://SRTHaishinKit/documentation/SRTHaishinKit/SRTPerformanceData/pktRcvFilterLossTotal":{"role":"symbol","fragments":[{"kind":"keyword","text":"let"},{"kind":"text","text":" "},{"kind":"identifier","text":"pktRcvFilterLossTotal"},{"kind":"text","text":": "},{"kind":"typeIdentifier","text":"Int32","preciseIdentifier":"s:s5Int32V"}],"url":"\/documentation\/srthaishinkit\/srtperformancedata\/pktrcvfilterlosstotal","type":"topic","kind":"symbol","identifier":"doc:\/\/SRTHaishinKit\/documentation\/SRTHaishinKit\/SRTPerformanceData\/pktRcvFilterLossTotal","title":"pktRcvFilterLossTotal","abstract":[{"type":"text","text":"The number of packet loss not coverable by filter"}]},"doc://SRTHaishinKit/documentation/SRTHaishinKit/SRTPerformanceData/usPktSndPeriod":{"type":"topic","identifier":"doc:\/\/SRTHaishinKit\/documentation\/SRTHaishinKit\/SRTPerformanceData\/usPktSndPeriod","title":"usPktSndPeriod","role":"symbol","url":"\/documentation\/srthaishinkit\/srtperformancedata\/uspktsndperiod","kind":"symbol","fragments":[{"kind":"keyword","text":"let"},{"kind":"text","text":" "},{"kind":"identifier","text":"usPktSndPeriod"},{"kind":"text","text":": "},{"preciseIdentifier":"s:Sd","kind":"typeIdentifier","text":"Double"}],"abstract":[{"type":"text","text":"The packet sending period, in microseconds"}]},"doc://SRTHaishinKit/documentation/SRTHaishinKit/SRTPerformanceData/byteSndBuf":{"url":"\/documentation\/srthaishinkit\/srtperformancedata\/bytesndbuf","fragments":[{"text":"let","kind":"keyword"},{"text":" ","kind":"text"},{"text":"byteSndBuf","kind":"identifier"},{"text":": ","kind":"text"},{"text":"Int32","kind":"typeIdentifier","preciseIdentifier":"s:s5Int32V"}],"role":"symbol","type":"topic","abstract":[{"type":"text","text":"The UnACKed bytes in UDT sender"}],"kind":"symbol","title":"byteSndBuf","identifier":"doc:\/\/SRTHaishinKit\/documentation\/SRTHaishinKit\/SRTPerformanceData\/byteSndBuf"},"doc://SRTHaishinKit/documentation/SRTHaishinKit/SRTPerformanceData/pktSndFilterExtra":{"abstract":[{"text":"The number of control packets supplied by packet filter","type":"text"}],"identifier":"doc:\/\/SRTHaishinKit\/documentation\/SRTHaishinKit\/SRTPerformanceData\/pktSndFilterExtra","url":"\/documentation\/srthaishinkit\/srtperformancedata\/pktsndfilterextra","title":"pktSndFilterExtra","role":"symbol","fragments":[{"kind":"keyword","text":"let"},{"kind":"text","text":" "},{"kind":"identifier","text":"pktSndFilterExtra"},{"kind":"text","text":": "},{"kind":"typeIdentifier","preciseIdentifier":"s:s5Int32V","text":"Int32"}],"kind":"symbol","type":"topic"},"doc://SRTHaishinKit/documentation/SRTHaishinKit/SRTPerformanceData/byteRetrans":{"kind":"symbol","type":"topic","fragments":[{"text":"let","kind":"keyword"},{"text":" ","kind":"text"},{"text":"byteRetrans","kind":"identifier"},{"text":": ","kind":"text"},{"text":"UInt64","kind":"typeIdentifier","preciseIdentifier":"s:s6UInt64V"}],"url":"\/documentation\/srthaishinkit\/srtperformancedata\/byteretrans","role":"symbol","abstract":[{"text":"The number of retransmitted bytes","type":"text"}],"identifier":"doc:\/\/SRTHaishinKit\/documentation\/SRTHaishinKit\/SRTPerformanceData\/byteRetrans","title":"byteRetrans"},"doc://SRTHaishinKit/documentation/SRTHaishinKit/SRTPerformanceData/byteSndDrop":{"type":"topic","title":"byteSndDrop","kind":"symbol","fragments":[{"kind":"keyword","text":"let"},{"text":" ","kind":"text"},{"text":"byteSndDrop","kind":"identifier"},{"text":": ","kind":"text"},{"text":"UInt64","kind":"typeIdentifier","preciseIdentifier":"s:s6UInt64V"}],"identifier":"doc:\/\/SRTHaishinKit\/documentation\/SRTHaishinKit\/SRTPerformanceData\/byteSndDrop","abstract":[{"text":"The number of too-late-to-send dropped bytes","type":"text"}],"url":"\/documentation\/srthaishinkit\/srtperformancedata\/bytesnddrop","role":"symbol"},"doc://SRTHaishinKit/documentation/SRTHaishinKit/SRTPerformanceData/pktSndFilterExtraTotal":{"role":"symbol","identifier":"doc:\/\/SRTHaishinKit\/documentation\/SRTHaishinKit\/SRTPerformanceData\/pktSndFilterExtraTotal","kind":"symbol","title":"pktSndFilterExtraTotal","abstract":[{"type":"text","text":"The number of control packets supplied by packet filter"}],"url":"\/documentation\/srthaishinkit\/srtperformancedata\/pktsndfilterextratotal","fragments":[{"text":"let","kind":"keyword"},{"text":" ","kind":"text"},{"text":"pktSndFilterExtraTotal","kind":"identifier"},{"text":": ","kind":"text"},{"text":"Int32","preciseIdentifier":"s:s5Int32V","kind":"typeIdentifier"}],"type":"topic"},"doc://SRTHaishinKit/documentation/SRTHaishinKit/SRTPerformanceData/pktSndBuf":{"url":"\/documentation\/srthaishinkit\/srtperformancedata\/pktsndbuf","abstract":[{"text":"The UnACKed packets in UDT sender","type":"text"}],"role":"symbol","identifier":"doc:\/\/SRTHaishinKit\/documentation\/SRTHaishinKit\/SRTPerformanceData\/pktSndBuf","fragments":[{"text":"let","kind":"keyword"},{"text":" ","kind":"text"},{"text":"pktSndBuf","kind":"identifier"},{"text":": ","kind":"text"},{"text":"Int32","preciseIdentifier":"s:s5Int32V","kind":"typeIdentifier"}],"type":"topic","title":"pktSndBuf","kind":"symbol"},"doc://SRTHaishinKit/documentation/SRTHaishinKit/SRTPerformanceData/pktRecvACK":{"type":"topic","abstract":[{"type":"text","text":"The number of received ACK packets"}],"kind":"symbol","title":"pktRecvACK","identifier":"doc:\/\/SRTHaishinKit\/documentation\/SRTHaishinKit\/SRTPerformanceData\/pktRecvACK","role":"symbol","fragments":[{"kind":"keyword","text":"let"},{"kind":"text","text":" "},{"kind":"identifier","text":"pktRecvACK"},{"kind":"text","text":": "},{"kind":"typeIdentifier","text":"Int32","preciseIdentifier":"s:s5Int32V"}],"url":"\/documentation\/srthaishinkit\/srtperformancedata\/pktrecvack"},"doc://SRTHaishinKit/documentation/SRTHaishinKit/SRTPerformanceData/byteSentTotal":{"abstract":[{"type":"text","text":"The total number of sent data bytes, including retransmissions"}],"identifier":"doc:\/\/SRTHaishinKit\/documentation\/SRTHaishinKit\/SRTPerformanceData\/byteSentTotal","url":"\/documentation\/srthaishinkit\/srtperformancedata\/bytesenttotal","type":"topic","role":"symbol","title":"byteSentTotal","fragments":[{"text":"let","kind":"keyword"},{"text":" ","kind":"text"},{"text":"byteSentTotal","kind":"identifier"},{"text":": ","kind":"text"},{"text":"UInt64","kind":"typeIdentifier","preciseIdentifier":"s:s6UInt64V"}],"kind":"symbol"},"doc://SRTHaishinKit/documentation/SRTHaishinKit/SRTPerformanceData/byteRcvDropTotal":{"identifier":"doc:\/\/SRTHaishinKit\/documentation\/SRTHaishinKit\/SRTPerformanceData\/byteRcvDropTotal","type":"topic","title":"byteRcvDropTotal","role":"symbol","url":"\/documentation\/srthaishinkit\/srtperformancedata\/bytercvdroptotal","abstract":[{"text":"The number of too-late-to play missing bytes (estimate based on average packet size)","type":"text"}],"kind":"symbol","fragments":[{"text":"let","kind":"keyword"},{"text":" ","kind":"text"},{"text":"byteRcvDropTotal","kind":"identifier"},{"text":": ","kind":"text"},{"preciseIdentifier":"s:s6UInt64V","text":"UInt64","kind":"typeIdentifier"}]},"doc://SRTHaishinKit/documentation/SRTHaishinKit/SRTPerformanceData/pktSent":{"identifier":"doc:\/\/SRTHaishinKit\/documentation\/SRTHaishinKit\/SRTPerformanceData\/pktSent","role":"symbol","title":"pktSent","url":"\/documentation\/srthaishinkit\/srtperformancedata\/pktsent","kind":"symbol","fragments":[{"kind":"keyword","text":"let"},{"kind":"text","text":" "},{"kind":"identifier","text":"pktSent"},{"kind":"text","text":": "},{"preciseIdentifier":"s:s5Int64V","kind":"typeIdentifier","text":"Int64"}],"abstract":[{"text":"The number of sent data packets, including retransmissions","type":"text"}],"type":"topic"},"doc://SRTHaishinKit/documentation/SRTHaishinKit/SRTPerformanceData/msRcvBuf":{"fragments":[{"kind":"keyword","text":"let"},{"kind":"text","text":" "},{"kind":"identifier","text":"msRcvBuf"},{"kind":"text","text":": "},{"kind":"typeIdentifier","text":"Int32","preciseIdentifier":"s:s5Int32V"}],"title":"msRcvBuf","type":"topic","kind":"symbol","url":"\/documentation\/srthaishinkit\/srtperformancedata\/msrcvbuf","role":"symbol","identifier":"doc:\/\/SRTHaishinKit\/documentation\/SRTHaishinKit\/SRTPerformanceData\/msRcvBuf","abstract":[{"type":"text","text":"The undelivered timespan (msec) of UDT receiver"}]},"doc://SRTHaishinKit/documentation/SRTHaishinKit/SRTPerformanceData/msRTT":{"type":"topic","fragments":[{"text":"let","kind":"keyword"},{"text":" ","kind":"text"},{"text":"msRTT","kind":"identifier"},{"text":": ","kind":"text"},{"text":"Double","kind":"typeIdentifier","preciseIdentifier":"s:Sd"}],"role":"symbol","abstract":[{"type":"text","text":"The RTT, in milliseconds"}],"url":"\/documentation\/srthaishinkit\/srtperformancedata\/msrtt","identifier":"doc:\/\/SRTHaishinKit\/documentation\/SRTHaishinKit\/SRTPerformanceData\/msRTT","title":"msRTT","kind":"symbol"},"doc://SRTHaishinKit/documentation/SRTHaishinKit/SRTPerformanceData/byteRcvUndecryptTotal":{"type":"topic","role":"symbol","kind":"symbol","abstract":[{"text":"The number of undecrypted bytes","type":"text"}],"identifier":"doc:\/\/SRTHaishinKit\/documentation\/SRTHaishinKit\/SRTPerformanceData\/byteRcvUndecryptTotal","fragments":[{"text":"let","kind":"keyword"},{"text":" ","kind":"text"},{"text":"byteRcvUndecryptTotal","kind":"identifier"},{"text":": ","kind":"text"},{"text":"UInt64","kind":"typeIdentifier","preciseIdentifier":"s:s6UInt64V"}],"url":"\/documentation\/srthaishinkit\/srtperformancedata\/bytercvundecrypttotal","title":"byteRcvUndecryptTotal"},"doc://SRTHaishinKit/documentation/SRTHaishinKit/SRTPerformanceData/msSndTsbPdDelay":{"type":"topic","kind":"symbol","fragments":[{"text":"let","kind":"keyword"},{"text":" ","kind":"text"},{"text":"msSndTsbPdDelay","kind":"identifier"},{"text":": ","kind":"text"},{"preciseIdentifier":"s:s5Int32V","text":"Int32","kind":"typeIdentifier"}],"identifier":"doc:\/\/SRTHaishinKit\/documentation\/SRTHaishinKit\/SRTPerformanceData\/msSndTsbPdDelay","url":"\/documentation\/srthaishinkit\/srtperformancedata\/mssndtsbpddelay","role":"symbol","title":"msSndTsbPdDelay","abstract":[{"text":"Timestamp-based Packet Delivery Delay","type":"text"}]},"doc://SRTHaishinKit/documentation/SRTHaishinKit/SRTPerformanceData":{"navigatorTitle":[{"text":"SRTPerformanceData","kind":"identifier"}],"fragments":[{"text":"struct","kind":"keyword"},{"text":" ","kind":"text"},{"text":"SRTPerformanceData","kind":"identifier"}],"abstract":[{"text":"The SRTPerformanceData represents the SRT’s performance statistics. This struct is wrapper for an CBytePerfMon.","type":"text"}],"kind":"symbol","type":"topic","title":"SRTPerformanceData","identifier":"doc:\/\/SRTHaishinKit\/documentation\/SRTHaishinKit\/SRTPerformanceData","url":"\/documentation\/srthaishinkit\/srtperformancedata","role":"symbol"},"doc://SRTHaishinKit/documentation/SRTHaishinKit/SRTPerformanceData/pktRcvFilterSupplyTotal":{"identifier":"doc:\/\/SRTHaishinKit\/documentation\/SRTHaishinKit\/SRTPerformanceData\/pktRcvFilterSupplyTotal","kind":"symbol","url":"\/documentation\/srthaishinkit\/srtperformancedata\/pktrcvfiltersupplytotal","abstract":[{"type":"text","text":"The number of packets that the filter supplied extra (e.g. FEC rebuilt)"}],"title":"pktRcvFilterSupplyTotal","type":"topic","fragments":[{"text":"let","kind":"keyword"},{"text":" ","kind":"text"},{"text":"pktRcvFilterSupplyTotal","kind":"identifier"},{"text":": ","kind":"text"},{"text":"Int32","preciseIdentifier":"s:s5Int32V","kind":"typeIdentifier"}],"role":"symbol"},"doc://SRTHaishinKit/documentation/SRTHaishinKit/SRTPerformanceData/mbpsSendRate":{"fragments":[{"text":"let","kind":"keyword"},{"text":" ","kind":"text"},{"text":"mbpsSendRate","kind":"identifier"},{"text":": ","kind":"text"},{"text":"Double","preciseIdentifier":"s:Sd","kind":"typeIdentifier"}],"kind":"symbol","type":"topic","url":"\/documentation\/srthaishinkit\/srtperformancedata\/mbpssendrate","identifier":"doc:\/\/SRTHaishinKit\/documentation\/SRTHaishinKit\/SRTPerformanceData\/mbpsSendRate","abstract":[{"text":"The sending rate in Mb\/s","type":"text"}],"role":"symbol","title":"mbpsSendRate"},"doc://SRTHaishinKit/documentation/SRTHaishinKit/SRTPerformanceData/byteRcvLoss":{"url":"\/documentation\/srthaishinkit\/srtperformancedata\/bytercvloss","fragments":[{"text":"let","kind":"keyword"},{"text":" ","kind":"text"},{"text":"byteRcvLoss","kind":"identifier"},{"text":": ","kind":"text"},{"text":"UInt64","kind":"typeIdentifier","preciseIdentifier":"s:s6UInt64V"}],"role":"symbol","abstract":[{"text":"The number of retransmitted bytes","type":"text"}],"type":"topic","kind":"symbol","identifier":"doc:\/\/SRTHaishinKit\/documentation\/SRTHaishinKit\/SRTPerformanceData\/byteRcvLoss","title":"byteRcvLoss"},"doc://SRTHaishinKit/documentation/SRTHaishinKit/SRTPerformanceData/mbpsMaxBW":{"url":"\/documentation\/srthaishinkit\/srtperformancedata\/mbpsmaxbw","kind":"symbol","role":"symbol","type":"topic","fragments":[{"text":"let","kind":"keyword"},{"text":" ","kind":"text"},{"text":"mbpsMaxBW","kind":"identifier"},{"text":": ","kind":"text"},{"text":"Double","kind":"typeIdentifier","preciseIdentifier":"s:Sd"}],"title":"mbpsMaxBW","abstract":[{"text":"The transmit Bandwidth ceiling (Mbps)","type":"text"}],"identifier":"doc:\/\/SRTHaishinKit\/documentation\/SRTHaishinKit\/SRTPerformanceData\/mbpsMaxBW"},"doc://SRTHaishinKit/documentation/SRTHaishinKit/SRTPerformanceData/msTimeStamp":{"type":"topic","fragments":[{"text":"let","kind":"keyword"},{"text":" ","kind":"text"},{"text":"msTimeStamp","kind":"identifier"},{"text":": ","kind":"text"},{"text":"Int64","kind":"typeIdentifier","preciseIdentifier":"s:s5Int64V"}],"identifier":"doc:\/\/SRTHaishinKit\/documentation\/SRTHaishinKit\/SRTPerformanceData\/msTimeStamp","kind":"symbol","role":"symbol","abstract":[{"type":"text","text":"The time since the UDT entity is started, in milliseconds."}],"title":"msTimeStamp","url":"\/documentation\/srthaishinkit\/srtperformancedata\/mstimestamp"},"doc://SRTHaishinKit/documentation/SRTHaishinKit/SRTPerformanceData/usSndDurationTotal":{"fragments":[{"kind":"keyword","text":"let"},{"kind":"text","text":" "},{"kind":"identifier","text":"usSndDurationTotal"},{"kind":"text","text":": "},{"kind":"typeIdentifier","text":"Int64","preciseIdentifier":"s:s5Int64V"}],"title":"usSndDurationTotal","abstract":[{"type":"text","text":"The total time duration when UDT is sending data (idle time exclusive)"}],"type":"topic","kind":"symbol","identifier":"doc:\/\/SRTHaishinKit\/documentation\/SRTHaishinKit\/SRTPerformanceData\/usSndDurationTotal","role":"symbol","url":"\/documentation\/srthaishinkit\/srtperformancedata\/ussnddurationtotal"},"doc://SRTHaishinKit/documentation/SRTHaishinKit/SRTPerformanceData/pktRecv":{"url":"\/documentation\/srthaishinkit\/srtperformancedata\/pktrecv","abstract":[{"text":"The number of received packets","type":"text"}],"kind":"symbol","title":"pktRecv","role":"symbol","identifier":"doc:\/\/SRTHaishinKit\/documentation\/SRTHaishinKit\/SRTPerformanceData\/pktRecv","fragments":[{"text":"let","kind":"keyword"},{"text":" ","kind":"text"},{"text":"pktRecv","kind":"identifier"},{"text":": ","kind":"text"},{"preciseIdentifier":"s:s5Int64V","text":"Int64","kind":"typeIdentifier"}],"type":"topic"},"doc://SRTHaishinKit/documentation/SRTHaishinKit/SRTPerformanceData/pktSndDropTotal":{"title":"pktSndDropTotal","kind":"symbol","identifier":"doc:\/\/SRTHaishinKit\/documentation\/SRTHaishinKit\/SRTPerformanceData\/pktSndDropTotal","role":"symbol","url":"\/documentation\/srthaishinkit\/srtperformancedata\/pktsnddroptotal","type":"topic","fragments":[{"text":"let","kind":"keyword"},{"text":" ","kind":"text"},{"text":"pktSndDropTotal","kind":"identifier"},{"text":": ","kind":"text"},{"preciseIdentifier":"s:s5Int32V","text":"Int32","kind":"typeIdentifier"}],"abstract":[{"type":"text","text":"The number of too-late-to-send dropped packets"}]},"doc://SRTHaishinKit/documentation/SRTHaishinKit/SRTPerformanceData/byteRecvTotal":{"url":"\/documentation\/srthaishinkit\/srtperformancedata\/byterecvtotal","title":"byteRecvTotal","identifier":"doc:\/\/SRTHaishinKit\/documentation\/SRTHaishinKit\/SRTPerformanceData\/byteRecvTotal","kind":"symbol","abstract":[{"type":"text","text":"The total number of received bytes"}],"type":"topic","role":"symbol","fragments":[{"text":"let","kind":"keyword"},{"text":" ","kind":"text"},{"text":"byteRecvTotal","kind":"identifier"},{"text":": ","kind":"text"},{"text":"UInt64","preciseIdentifier":"s:s6UInt64V","kind":"typeIdentifier"}]},"doc://SRTHaishinKit/documentation/SRTHaishinKit/SRTPerformanceData/msRcvTsbPdDelay":{"fragments":[{"kind":"keyword","text":"let"},{"kind":"text","text":" "},{"kind":"identifier","text":"msRcvTsbPdDelay"},{"kind":"text","text":": "},{"preciseIdentifier":"s:s5Int32V","kind":"typeIdentifier","text":"Int32"}],"kind":"symbol","url":"\/documentation\/srthaishinkit\/srtperformancedata\/msrcvtsbpddelay","abstract":[{"text":"The Timestamp-based Packet Delivery Delay","type":"text"}],"identifier":"doc:\/\/SRTHaishinKit\/documentation\/SRTHaishinKit\/SRTPerformanceData\/msRcvTsbPdDelay","role":"symbol","title":"msRcvTsbPdDelay","type":"topic"},"doc://SRTHaishinKit/documentation/SRTHaishinKit/SRTPerformanceData/pktSentACKTotal":{"abstract":[{"type":"text","text":"The total number of sent ACK packets"}],"type":"topic","identifier":"doc:\/\/SRTHaishinKit\/documentation\/SRTHaishinKit\/SRTPerformanceData\/pktSentACKTotal","kind":"symbol","fragments":[{"text":"let","kind":"keyword"},{"text":" ","kind":"text"},{"text":"pktSentACKTotal","kind":"identifier"},{"text":": ","kind":"text"},{"text":"Int32","preciseIdentifier":"s:s5Int32V","kind":"typeIdentifier"}],"role":"symbol","title":"pktSentACKTotal","url":"\/documentation\/srthaishinkit\/srtperformancedata\/pktsentacktotal"},"doc://SRTHaishinKit/documentation/SRTHaishinKit/SRTPerformanceData/pktRcvLossTotal":{"type":"topic","url":"\/documentation\/srthaishinkit\/srtperformancedata\/pktrcvlosstotal","title":"pktRcvLossTotal","fragments":[{"kind":"keyword","text":"let"},{"kind":"text","text":" "},{"kind":"identifier","text":"pktRcvLossTotal"},{"kind":"text","text":": "},{"kind":"typeIdentifier","preciseIdentifier":"s:s5Int32V","text":"Int32"}],"role":"symbol","abstract":[{"type":"text","text":"The total number of lost packets (receiver side)"}],"identifier":"doc:\/\/SRTHaishinKit\/documentation\/SRTHaishinKit\/SRTPerformanceData\/pktRcvLossTotal","kind":"symbol"},"doc://SRTHaishinKit/documentation/SRTHaishinKit/SRTPerformanceData/pktRcvBuf":{"title":"pktRcvBuf","identifier":"doc:\/\/SRTHaishinKit\/documentation\/SRTHaishinKit\/SRTPerformanceData\/pktRcvBuf","fragments":[{"kind":"keyword","text":"let"},{"kind":"text","text":" "},{"kind":"identifier","text":"pktRcvBuf"},{"text":": ","kind":"text"},{"text":"Int32","preciseIdentifier":"s:s5Int32V","kind":"typeIdentifier"}],"abstract":[{"text":"Undelivered packets in UDT receiver","type":"text"}],"type":"topic","role":"symbol","url":"\/documentation\/srthaishinkit\/srtperformancedata\/pktrcvbuf","kind":"symbol"},"doc://SRTHaishinKit/documentation/SRTHaishinKit/SRTPerformanceData/byteRcvUndecrypt":{"title":"byteRcvUndecrypt","fragments":[{"kind":"keyword","text":"let"},{"kind":"text","text":" "},{"kind":"identifier","text":"byteRcvUndecrypt"},{"kind":"text","text":": "},{"kind":"typeIdentifier","preciseIdentifier":"s:s6UInt64V","text":"UInt64"}],"identifier":"doc:\/\/SRTHaishinKit\/documentation\/SRTHaishinKit\/SRTPerformanceData\/byteRcvUndecrypt","role":"symbol","kind":"symbol","abstract":[{"type":"text","text":"The number of undecrypted bytes"}],"type":"topic","url":"\/documentation\/srthaishinkit\/srtperformancedata\/bytercvundecrypt"},"doc://SRTHaishinKit/documentation/SRTHaishinKit/SRTPerformanceData/pktRetransTotal":{"title":"pktRetransTotal","kind":"symbol","identifier":"doc:\/\/SRTHaishinKit\/documentation\/SRTHaishinKit\/SRTPerformanceData\/pktRetransTotal","role":"symbol","url":"\/documentation\/srthaishinkit\/srtperformancedata\/pktretranstotal","type":"topic","fragments":[{"text":"let","kind":"keyword"},{"text":" ","kind":"text"},{"text":"pktRetransTotal","kind":"identifier"},{"text":": ","kind":"text"},{"text":"Int32","kind":"typeIdentifier","preciseIdentifier":"s:s5Int32V"}],"abstract":[{"text":"The total number of retransmitted packets","type":"text"}]},"doc://SRTHaishinKit/documentation/SRTHaishinKit/SRTPerformanceData/byteRcvLossTotal":{"title":"byteRcvLossTotal","identifier":"doc:\/\/SRTHaishinKit\/documentation\/SRTHaishinKit\/SRTPerformanceData\/byteRcvLossTotal","fragments":[{"kind":"keyword","text":"let"},{"kind":"text","text":" "},{"kind":"identifier","text":"byteRcvLossTotal"},{"kind":"text","text":": "},{"preciseIdentifier":"s:s6UInt64V","kind":"typeIdentifier","text":"UInt64"}],"role":"symbol","type":"topic","url":"\/documentation\/srthaishinkit\/srtperformancedata\/bytercvlosstotal","abstract":[{"text":"The total number of lost bytes","type":"text"}],"kind":"symbol"},"doc://SRTHaishinKit/documentation/SRTHaishinKit/SRTPerformanceData/pktSentACK":{"url":"\/documentation\/srthaishinkit\/srtperformancedata\/pktsentack","abstract":[{"text":"The number of sent ACK packets","type":"text"}],"role":"symbol","identifier":"doc:\/\/SRTHaishinKit\/documentation\/SRTHaishinKit\/SRTPerformanceData\/pktSentACK","fragments":[{"kind":"keyword","text":"let"},{"kind":"text","text":" "},{"kind":"identifier","text":"pktSentACK"},{"kind":"text","text":": "},{"kind":"typeIdentifier","text":"Int32","preciseIdentifier":"s:s5Int32V"}],"type":"topic","title":"pktSentACK","kind":"symbol"},"doc://SRTHaishinKit/documentation/SRTHaishinKit/SRTPerformanceData/byteRecv":{"identifier":"doc:\/\/SRTHaishinKit\/documentation\/SRTHaishinKit\/SRTPerformanceData\/byteRecv","abstract":[{"text":"The number of received bytes","type":"text"}],"url":"\/documentation\/srthaishinkit\/srtperformancedata\/byterecv","fragments":[{"kind":"keyword","text":"let"},{"kind":"text","text":" "},{"kind":"identifier","text":"byteRecv"},{"kind":"text","text":": "},{"preciseIdentifier":"s:s6UInt64V","kind":"typeIdentifier","text":"UInt64"}],"type":"topic","kind":"symbol","title":"byteRecv","role":"symbol"},"doc://SRTHaishinKit/documentation/SRTHaishinKit/SRTPerformanceData/msSndBuf":{"identifier":"doc:\/\/SRTHaishinKit\/documentation\/SRTHaishinKit\/SRTPerformanceData\/msSndBuf","title":"msSndBuf","type":"topic","abstract":[{"type":"text","text":"The UnACKed timespan (msec) of UDT sender"}],"url":"\/documentation\/srthaishinkit\/srtperformancedata\/mssndbuf","kind":"symbol","role":"symbol","fragments":[{"text":"let","kind":"keyword"},{"text":" ","kind":"text"},{"text":"msSndBuf","kind":"identifier"},{"text":": ","kind":"text"},{"text":"Int32","kind":"typeIdentifier","preciseIdentifier":"s:s5Int32V"}]},"doc://SRTHaishinKit/documentation/SRTHaishinKit/SRTPerformanceData/byteRcvBuf":{"abstract":[{"text":"The undelivered bytes of UDT receiver","type":"text"}],"kind":"symbol","role":"symbol","url":"\/documentation\/srthaishinkit\/srtperformancedata\/bytercvbuf","title":"byteRcvBuf","fragments":[{"text":"let","kind":"keyword"},{"text":" ","kind":"text"},{"text":"byteRcvBuf","kind":"identifier"},{"text":": ","kind":"text"},{"text":"Int32","preciseIdentifier":"s:s5Int32V","kind":"typeIdentifier"}],"type":"topic","identifier":"doc:\/\/SRTHaishinKit\/documentation\/SRTHaishinKit\/SRTPerformanceData\/byteRcvBuf"},"doc://SRTHaishinKit/documentation/SRTHaishinKit/SRTPerformanceData/pktRecvNAK":{"url":"\/documentation\/srthaishinkit\/srtperformancedata\/pktrecvnak","title":"pktRecvNAK","kind":"symbol","abstract":[{"text":"The number of received NAK packets","type":"text"}],"identifier":"doc:\/\/SRTHaishinKit\/documentation\/SRTHaishinKit\/SRTPerformanceData\/pktRecvNAK","fragments":[{"text":"let","kind":"keyword"},{"text":" ","kind":"text"},{"text":"pktRecvNAK","kind":"identifier"},{"text":": ","kind":"text"},{"text":"Int32","kind":"typeIdentifier","preciseIdentifier":"s:s5Int32V"}],"type":"topic","role":"symbol"},"doc://SRTHaishinKit/documentation/SRTHaishinKit/SRTPerformanceData/pktRcvFilterExtraTotal":{"title":"pktRcvFilterExtraTotal","kind":"symbol","abstract":[{"text":"The number of control packets received and not supplied back","type":"text"}],"url":"\/documentation\/srthaishinkit\/srtperformancedata\/pktrcvfilterextratotal","identifier":"doc:\/\/SRTHaishinKit\/documentation\/SRTHaishinKit\/SRTPerformanceData\/pktRcvFilterExtraTotal","fragments":[{"kind":"keyword","text":"let"},{"kind":"text","text":" "},{"kind":"identifier","text":"pktRcvFilterExtraTotal"},{"kind":"text","text":": "},{"kind":"typeIdentifier","preciseIdentifier":"s:s5Int32V","text":"Int32"}],"role":"symbol","type":"topic"},"doc://SRTHaishinKit/documentation/SRTHaishinKit/SRTPerformanceData/pktRetrans":{"role":"symbol","url":"\/documentation\/srthaishinkit\/srtperformancedata\/pktretrans","identifier":"doc:\/\/SRTHaishinKit\/documentation\/SRTHaishinKit\/SRTPerformanceData\/pktRetrans","kind":"symbol","fragments":[{"kind":"keyword","text":"let"},{"text":" ","kind":"text"},{"text":"pktRetrans","kind":"identifier"},{"text":": ","kind":"text"},{"text":"Int32","kind":"typeIdentifier","preciseIdentifier":"s:s5Int32V"}],"title":"pktRetrans","abstract":[{"type":"text","text":"The number of retransmitted packets"}],"type":"topic"},"doc://SRTHaishinKit/documentation/SRTHaishinKit/SRTPerformanceData/pktRcvLoss":{"type":"topic","url":"\/documentation\/srthaishinkit\/srtperformancedata\/pktrcvloss","abstract":[{"text":"The number of lost packets (receiver side)","type":"text"}],"role":"symbol","kind":"symbol","fragments":[{"text":"let","kind":"keyword"},{"text":" ","kind":"text"},{"text":"pktRcvLoss","kind":"identifier"},{"text":": ","kind":"text"},{"text":"Int32","preciseIdentifier":"s:s5Int32V","kind":"typeIdentifier"}],"identifier":"doc:\/\/SRTHaishinKit\/documentation\/SRTHaishinKit\/SRTPerformanceData\/pktRcvLoss","title":"pktRcvLoss"},"doc://SRTHaishinKit/documentation/SRTHaishinKit/SRTPerformanceData/mbpsRecvRate":{"abstract":[{"text":"The receiving rate in Mb\/s","type":"text"}],"type":"topic","url":"\/documentation\/srthaishinkit\/srtperformancedata\/mbpsrecvrate","role":"symbol","kind":"symbol","identifier":"doc:\/\/SRTHaishinKit\/documentation\/SRTHaishinKit\/SRTPerformanceData\/mbpsRecvRate","fragments":[{"text":"let","kind":"keyword"},{"text":" ","kind":"text"},{"text":"mbpsRecvRate","kind":"identifier"},{"text":": ","kind":"text"},{"text":"Double","kind":"typeIdentifier","preciseIdentifier":"s:Sd"}],"title":"mbpsRecvRate"},"doc://SRTHaishinKit/documentation/SRTHaishinKit/SRTPerformanceData/pktFlowWindow":{"fragments":[{"text":"let","kind":"keyword"},{"text":" ","kind":"text"},{"text":"pktFlowWindow","kind":"identifier"},{"text":": ","kind":"text"},{"preciseIdentifier":"s:s5Int32V","text":"Int32","kind":"typeIdentifier"}],"kind":"symbol","url":"\/documentation\/srthaishinkit\/srtperformancedata\/pktflowwindow","role":"symbol","identifier":"doc:\/\/SRTHaishinKit\/documentation\/SRTHaishinKit\/SRTPerformanceData\/pktFlowWindow","abstract":[{"type":"text","text":"The flow window size, in number of packets"}],"type":"topic","title":"pktFlowWindow"},"doc://SRTHaishinKit/s8SendableP":{"identifier":"doc:\/\/SRTHaishinKit\/s8SendableP","title":"Swift.Sendable","type":"unresolvable"},"doc://SRTHaishinKit/documentation/SRTHaishinKit/SRTPerformanceData/pktSentNAKTotal":{"identifier":"doc:\/\/SRTHaishinKit\/documentation\/SRTHaishinKit\/SRTPerformanceData\/pktSentNAKTotal","fragments":[{"kind":"keyword","text":"let"},{"kind":"text","text":" "},{"kind":"identifier","text":"pktSentNAKTotal"},{"kind":"text","text":": "},{"preciseIdentifier":"s:s5Int32V","kind":"typeIdentifier","text":"Int32"}],"title":"pktSentNAKTotal","abstract":[{"type":"text","text":"The total number of sent NAK packets"}],"role":"symbol","kind":"symbol","type":"topic","url":"\/documentation\/srthaishinkit\/srtperformancedata\/pktsentnaktotal"},"doc://SRTHaishinKit/documentation/SRTHaishinKit/SRTPerformanceData/usSndDuration":{"title":"usSndDuration","type":"topic","role":"symbol","abstract":[{"text":"The busy sending time (i.e., idle time exclusive)","type":"text"}],"identifier":"doc:\/\/SRTHaishinKit\/documentation\/SRTHaishinKit\/SRTPerformanceData\/usSndDuration","url":"\/documentation\/srthaishinkit\/srtperformancedata\/ussndduration","kind":"symbol","fragments":[{"text":"let","kind":"keyword"},{"text":" ","kind":"text"},{"text":"usSndDuration","kind":"identifier"},{"text":": ","kind":"text"},{"text":"Int64","kind":"typeIdentifier","preciseIdentifier":"s:s5Int64V"}]},"doc://SRTHaishinKit/documentation/SRTHaishinKit/SRTPerformanceData/mbpsBandwidth":{"kind":"symbol","identifier":"doc:\/\/SRTHaishinKit\/documentation\/SRTHaishinKit\/SRTPerformanceData\/mbpsBandwidth","abstract":[{"type":"text","text":"The estimated bandwidth, in Mb\/s"}],"role":"symbol","title":"mbpsBandwidth","type":"topic","url":"\/documentation\/srthaishinkit\/srtperformancedata\/mbpsbandwidth","fragments":[{"kind":"keyword","text":"let"},{"kind":"text","text":" "},{"kind":"identifier","text":"mbpsBandwidth"},{"kind":"text","text":": "},{"preciseIdentifier":"s:Sd","kind":"typeIdentifier","text":"Double"}]},"doc://SRTHaishinKit/documentation/SRTHaishinKit/SRTPerformanceData/pktRecvACKTotal":{"kind":"symbol","type":"topic","role":"symbol","title":"pktRecvACKTotal","identifier":"doc:\/\/SRTHaishinKit\/documentation\/SRTHaishinKit\/SRTPerformanceData\/pktRecvACKTotal","url":"\/documentation\/srthaishinkit\/srtperformancedata\/pktrecvacktotal","abstract":[{"text":"The total number of received ACK packets","type":"text"}],"fragments":[{"kind":"keyword","text":"let"},{"kind":"text","text":" "},{"kind":"identifier","text":"pktRecvACKTotal"},{"kind":"text","text":": "},{"kind":"typeIdentifier","preciseIdentifier":"s:s5Int32V","text":"Int32"}]},"doc://SRTHaishinKit/documentation/SRTHaishinKit/SRTPerformanceData/byteMSS":{"type":"topic","role":"symbol","kind":"symbol","title":"byteMSS","url":"\/documentation\/srthaishinkit\/srtperformancedata\/bytemss","abstract":[{"type":"text","text":"The MTU"}],"identifier":"doc:\/\/SRTHaishinKit\/documentation\/SRTHaishinKit\/SRTPerformanceData\/byteMSS","fragments":[{"kind":"keyword","text":"let"},{"kind":"text","text":" "},{"kind":"identifier","text":"byteMSS"},{"kind":"text","text":": "},{"kind":"typeIdentifier","preciseIdentifier":"s:s5Int32V","text":"Int32"}]},"doc://SRTHaishinKit/documentation/SRTHaishinKit/SRTPerformanceData/byteAvailSndBuf":{"role":"symbol","identifier":"doc:\/\/SRTHaishinKit\/documentation\/SRTHaishinKit\/SRTPerformanceData\/byteAvailSndBuf","abstract":[{"type":"text","text":"The available UDT sender buffer size"}],"url":"\/documentation\/srthaishinkit\/srtperformancedata\/byteavailsndbuf","kind":"symbol","type":"topic","title":"byteAvailSndBuf","fragments":[{"text":"let","kind":"keyword"},{"text":" ","kind":"text"},{"text":"byteAvailSndBuf","kind":"identifier"},{"text":": ","kind":"text"},{"text":"Int32","kind":"typeIdentifier","preciseIdentifier":"s:s5Int32V"}]},"doc://SRTHaishinKit/documentation/SRTHaishinKit/SRTPerformanceData/byteRetransTotal":{"url":"\/documentation\/srthaishinkit\/srtperformancedata\/byteretranstotal","role":"symbol","type":"topic","identifier":"doc:\/\/SRTHaishinKit\/documentation\/SRTHaishinKit\/SRTPerformanceData\/byteRetransTotal","title":"byteRetransTotal","fragments":[{"text":"let","kind":"keyword"},{"text":" ","kind":"text"},{"text":"byteRetransTotal","kind":"identifier"},{"text":": ","kind":"text"},{"preciseIdentifier":"s:s6UInt64V","text":"UInt64","kind":"typeIdentifier"}],"abstract":[{"type":"text","text":"The total number of retransmitted bytes"}],"kind":"symbol"},"doc://SRTHaishinKit/documentation/SRTHaishinKit/SRTPerformanceData/pktCongestionWindow":{"identifier":"doc:\/\/SRTHaishinKit\/documentation\/SRTHaishinKit\/SRTPerformanceData\/pktCongestionWindow","fragments":[{"text":"let","kind":"keyword"},{"text":" ","kind":"text"},{"text":"pktCongestionWindow","kind":"identifier"},{"text":": ","kind":"text"},{"text":"Int32","kind":"typeIdentifier","preciseIdentifier":"s:s5Int32V"}],"type":"topic","url":"\/documentation\/srthaishinkit\/srtperformancedata\/pktcongestionwindow","title":"pktCongestionWindow","abstract":[{"text":"The congestion window size, in number of packets","type":"text"}],"kind":"symbol","role":"symbol"},"doc://SRTHaishinKit/documentation/SRTHaishinKit/SRTPerformanceData/pktRcvFilterLoss":{"role":"symbol","identifier":"doc:\/\/SRTHaishinKit\/documentation\/SRTHaishinKit\/SRTPerformanceData\/pktRcvFilterLoss","fragments":[{"kind":"keyword","text":"let"},{"kind":"text","text":" "},{"kind":"identifier","text":"pktRcvFilterLoss"},{"kind":"text","text":": "},{"preciseIdentifier":"s:s5Int32V","kind":"typeIdentifier","text":"Int32"}],"kind":"symbol","title":"pktRcvFilterLoss","type":"topic","abstract":[{"type":"text","text":"The number of packet loss not coverable by filter"}],"url":"\/documentation\/srthaishinkit\/srtperformancedata\/pktrcvfilterloss"},"doc://SRTHaishinKit/documentation/SRTHaishinKit/SRTPerformanceData/pktRcvFilterSupply":{"title":"pktRcvFilterSupply","role":"symbol","kind":"symbol","abstract":[{"type":"text","text":"The number of packets that the filter supplied extra (e.g. FEC rebuilt)"}],"type":"topic","fragments":[{"kind":"keyword","text":"let"},{"kind":"text","text":" "},{"kind":"identifier","text":"pktRcvFilterSupply"},{"kind":"text","text":": "},{"kind":"typeIdentifier","preciseIdentifier":"s:s5Int32V","text":"Int32"}],"identifier":"doc:\/\/SRTHaishinKit\/documentation\/SRTHaishinKit\/SRTPerformanceData\/pktRcvFilterSupply","url":"\/documentation\/srthaishinkit\/srtperformancedata\/pktrcvfiltersupply"},"doc://SRTHaishinKit/documentation/SRTHaishinKit":{"identifier":"doc:\/\/SRTHaishinKit\/documentation\/SRTHaishinKit","type":"topic","abstract":[{"type":"text","text":"This module supports the SRT protocol."}],"kind":"symbol","title":"SRTHaishinKit","role":"collection","url":"\/documentation\/srthaishinkit"},"doc://SRTHaishinKit/documentation/SRTHaishinKit/SRTPerformanceData/pktRcvRetrans":{"kind":"symbol","abstract":[{"type":"text","text":"The number of retransmitted packets received"}],"title":"pktRcvRetrans","type":"topic","url":"\/documentation\/srthaishinkit\/srtperformancedata\/pktrcvretrans","role":"symbol","fragments":[{"text":"let","kind":"keyword"},{"text":" ","kind":"text"},{"text":"pktRcvRetrans","kind":"identifier"},{"text":": ","kind":"text"},{"preciseIdentifier":"s:s5Int32V","text":"Int32","kind":"typeIdentifier"}],"identifier":"doc:\/\/SRTHaishinKit\/documentation\/SRTHaishinKit\/SRTPerformanceData\/pktRcvRetrans"},"doc://SRTHaishinKit/documentation/SRTHaishinKit/SRTPerformanceData/pktRcvDrop":{"identifier":"doc:\/\/SRTHaishinKit\/documentation\/SRTHaishinKit\/SRTPerformanceData\/pktRcvDrop","url":"\/documentation\/srthaishinkit\/srtperformancedata\/pktrcvdrop","type":"topic","role":"symbol","abstract":[{"type":"text","text":"The number of too-late-to play missing packets"}],"kind":"symbol","title":"pktRcvDrop","fragments":[{"text":"let","kind":"keyword"},{"text":" ","kind":"text"},{"text":"pktRcvDrop","kind":"identifier"},{"text":": ","kind":"text"},{"text":"Int32","kind":"typeIdentifier","preciseIdentifier":"s:s5Int32V"}]},"doc://SRTHaishinKit/documentation/SRTHaishinKit/SRTPerformanceData/pktRcvDropTotal":{"type":"topic","kind":"symbol","identifier":"doc:\/\/SRTHaishinKit\/documentation\/SRTHaishinKit\/SRTPerformanceData\/pktRcvDropTotal","role":"symbol","fragments":[{"kind":"keyword","text":"let"},{"kind":"text","text":" "},{"kind":"identifier","text":"pktRcvDropTotal"},{"kind":"text","text":": "},{"preciseIdentifier":"s:s5Int32V","kind":"typeIdentifier","text":"Int32"}],"abstract":[{"type":"text","text":"The number of too-late-to play missing packets"}],"url":"\/documentation\/srthaishinkit\/srtperformancedata\/pktrcvdroptotal","title":"pktRcvDropTotal"},"doc://SRTHaishinKit/documentation/SRTHaishinKit/SRTPerformanceData/pktSentTotal":{"role":"symbol","kind":"symbol","abstract":[{"type":"text","text":"The total number of sent data packets, including retransmissions."}],"type":"topic","title":"pktSentTotal","url":"\/documentation\/srthaishinkit\/srtperformancedata\/pktsenttotal","identifier":"doc:\/\/SRTHaishinKit\/documentation\/SRTHaishinKit\/SRTPerformanceData\/pktSentTotal","fragments":[{"text":"let","kind":"keyword"},{"text":" ","kind":"text"},{"text":"pktSentTotal","kind":"identifier"},{"text":": ","kind":"text"},{"text":"Int64","preciseIdentifier":"s:s5Int64V","kind":"typeIdentifier"}]},"doc://SRTHaishinKit/documentation/SRTHaishinKit/SRTPerformanceData/pktSndLoss":{"kind":"symbol","fragments":[{"text":"let","kind":"keyword"},{"text":" ","kind":"text"},{"text":"pktSndLoss","kind":"identifier"},{"text":": ","kind":"text"},{"text":"Int32","kind":"typeIdentifier","preciseIdentifier":"s:s5Int32V"}],"abstract":[{"type":"text","text":"The number of lost packets (sender side)"}],"identifier":"doc:\/\/SRTHaishinKit\/documentation\/SRTHaishinKit\/SRTPerformanceData\/pktSndLoss","type":"topic","role":"symbol","url":"\/documentation\/srthaishinkit\/srtperformancedata\/pktsndloss","title":"pktSndLoss"},"doc://SRTHaishinKit/documentation/SRTHaishinKit/SRTPerformanceData/pktRecvTotal":{"identifier":"doc:\/\/SRTHaishinKit\/documentation\/SRTHaishinKit\/SRTPerformanceData\/pktRecvTotal","title":"pktRecvTotal","kind":"symbol","type":"topic","url":"\/documentation\/srthaishinkit\/srtperformancedata\/pktrecvtotal","fragments":[{"kind":"keyword","text":"let"},{"kind":"text","text":" "},{"kind":"identifier","text":"pktRecvTotal"},{"kind":"text","text":": "},{"preciseIdentifier":"s:s5Int64V","kind":"typeIdentifier","text":"Int64"}],"abstract":[{"type":"text","text":"The total number of received packets."}],"role":"symbol"},"doc://SRTHaishinKit/documentation/SRTHaishinKit/SRTPerformanceData/pktRecvNAKTotal":{"type":"topic","abstract":[{"type":"text","text":"The total number of received NAK packets"}],"identifier":"doc:\/\/SRTHaishinKit\/documentation\/SRTHaishinKit\/SRTPerformanceData\/pktRecvNAKTotal","title":"pktRecvNAKTotal","kind":"symbol","fragments":[{"kind":"keyword","text":"let"},{"kind":"text","text":" "},{"kind":"identifier","text":"pktRecvNAKTotal"},{"kind":"text","text":": "},{"kind":"typeIdentifier","preciseIdentifier":"s:s5Int32V","text":"Int32"}],"url":"\/documentation\/srthaishinkit\/srtperformancedata\/pktrecvnaktotal","role":"symbol"},"doc://SRTHaishinKit/documentation/SRTHaishinKit/SRTPerformanceData/pktReorderDistance":{"role":"symbol","kind":"symbol","identifier":"doc:\/\/SRTHaishinKit\/documentation\/SRTHaishinKit\/SRTPerformanceData\/pktReorderDistance","abstract":[{"type":"text","text":"The size of order discrepancy in received sequences"}],"fragments":[{"text":"let","kind":"keyword"},{"text":" ","kind":"text"},{"text":"pktReorderDistance","kind":"identifier"},{"text":": ","kind":"text"},{"text":"Int32","kind":"typeIdentifier","preciseIdentifier":"s:s5Int32V"}],"type":"topic","title":"pktReorderDistance","url":"\/documentation\/srthaishinkit\/srtperformancedata\/pktreorderdistance"},"doc://SRTHaishinKit/documentation/SRTHaishinKit/SRTPerformanceData/pktFlightSize":{"identifier":"doc:\/\/SRTHaishinKit\/documentation\/SRTHaishinKit\/SRTPerformanceData\/pktFlightSize","title":"pktFlightSize","role":"symbol","abstract":[{"type":"text","text":"The number of packets on flight"}],"type":"topic","url":"\/documentation\/srthaishinkit\/srtperformancedata\/pktflightsize","kind":"symbol","fragments":[{"text":"let","kind":"keyword"},{"text":" ","kind":"text"},{"text":"pktFlightSize","kind":"identifier"},{"text":": ","kind":"text"},{"text":"Int32","kind":"typeIdentifier","preciseIdentifier":"s:s5Int32V"}]},"doc://SRTHaishinKit/documentation/SRTHaishinKit/SRTPerformanceData/byteRcvDrop":{"fragments":[{"kind":"keyword","text":"let"},{"kind":"text","text":" "},{"kind":"identifier","text":"byteRcvDrop"},{"kind":"text","text":": "},{"preciseIdentifier":"s:s6UInt64V","kind":"typeIdentifier","text":"UInt64"}],"abstract":[{"type":"text","text":"The number of too-late-to play missing bytes (estimate based on average packet size)"}],"role":"symbol","url":"\/documentation\/srthaishinkit\/srtperformancedata\/bytercvdrop","title":"byteRcvDrop","identifier":"doc:\/\/SRTHaishinKit\/documentation\/SRTHaishinKit\/SRTPerformanceData\/byteRcvDrop","type":"topic","kind":"symbol"},"doc://SRTHaishinKit/documentation/SRTHaishinKit/SRTPerformanceData/pktRcvUndecrypt":{"url":"\/documentation\/srthaishinkit\/srtperformancedata\/pktrcvundecrypt","abstract":[{"type":"text","text":"The number of undecrypted packets"}],"role":"symbol","fragments":[{"text":"let","kind":"keyword"},{"text":" ","kind":"text"},{"text":"pktRcvUndecrypt","kind":"identifier"},{"text":": ","kind":"text"},{"preciseIdentifier":"s:s5Int32V","text":"Int32","kind":"typeIdentifier"}],"kind":"symbol","title":"pktRcvUndecrypt","identifier":"doc:\/\/SRTHaishinKit\/documentation\/SRTHaishinKit\/SRTPerformanceData\/pktRcvUndecrypt","type":"topic"},"doc://SRTHaishinKit/documentation/SRTHaishinKit/SRTPerformanceData/pktSndDrop":{"role":"symbol","type":"topic","abstract":[{"type":"text","text":"The number of too-late-to-send dropped packets"}],"fragments":[{"kind":"keyword","text":"let"},{"kind":"text","text":" "},{"kind":"identifier","text":"pktSndDrop"},{"kind":"text","text":": "},{"preciseIdentifier":"s:s5Int32V","kind":"typeIdentifier","text":"Int32"}],"identifier":"doc:\/\/SRTHaishinKit\/documentation\/SRTHaishinKit\/SRTPerformanceData\/pktSndDrop","title":"pktSndDrop","kind":"symbol","url":"\/documentation\/srthaishinkit\/srtperformancedata\/pktsnddrop"},"doc://SRTHaishinKit/documentation/SRTHaishinKit/SRTPerformanceData/pktRcvFilterExtra":{"role":"symbol","url":"\/documentation\/srthaishinkit\/srtperformancedata\/pktrcvfilterextra","identifier":"doc:\/\/SRTHaishinKit\/documentation\/SRTHaishinKit\/SRTPerformanceData\/pktRcvFilterExtra","title":"pktRcvFilterExtra","kind":"symbol","abstract":[{"type":"text","text":"The number of control packets received and not supplied back"}],"fragments":[{"kind":"keyword","text":"let"},{"kind":"text","text":" "},{"kind":"identifier","text":"pktRcvFilterExtra"},{"kind":"text","text":": "},{"preciseIdentifier":"s:s5Int32V","kind":"typeIdentifier","text":"Int32"}],"type":"topic"},"doc://SRTHaishinKit/documentation/SRTHaishinKit/SRTPerformanceData/pktRcvBelated":{"role":"symbol","kind":"symbol","fragments":[{"text":"let","kind":"keyword"},{"text":" ","kind":"text"},{"text":"pktRcvBelated","kind":"identifier"},{"text":": ","kind":"text"},{"text":"Int64","kind":"typeIdentifier","preciseIdentifier":"s:s5Int64V"}],"url":"\/documentation\/srthaishinkit\/srtperformancedata\/pktrcvbelated","identifier":"doc:\/\/SRTHaishinKit\/documentation\/SRTHaishinKit\/SRTPerformanceData\/pktRcvBelated","type":"topic","title":"pktRcvBelated","abstract":[{"text":"The number of received AND IGNORED packets due to having come too late","type":"text"}]},"doc://SRTHaishinKit/documentation/SRTHaishinKit/SRTPerformanceData/pktRcvAvgBelatedTime":{"role":"symbol","title":"pktRcvAvgBelatedTime","type":"topic","kind":"symbol","identifier":"doc:\/\/SRTHaishinKit\/documentation\/SRTHaishinKit\/SRTPerformanceData\/pktRcvAvgBelatedTime","abstract":[{"text":"The average time of packet delay for belated packets (packets with sequence past the ACK)","type":"text"}],"url":"\/documentation\/srthaishinkit\/srtperformancedata\/pktrcvavgbelatedtime","fragments":[{"text":"let","kind":"keyword"},{"text":" ","kind":"text"},{"text":"pktRcvAvgBelatedTime","kind":"identifier"},{"text":": ","kind":"text"},{"text":"Double","preciseIdentifier":"s:Sd","kind":"typeIdentifier"}]},"doc://SRTHaishinKit/documentation/SRTHaishinKit/SRTPerformanceData/pktSentNAK":{"title":"pktSentNAK","role":"symbol","abstract":[{"type":"text","text":"The number of sent NAK packets"}],"url":"\/documentation\/srthaishinkit\/srtperformancedata\/pktsentnak","identifier":"doc:\/\/SRTHaishinKit\/documentation\/SRTHaishinKit\/SRTPerformanceData\/pktSentNAK","type":"topic","fragments":[{"kind":"keyword","text":"let"},{"kind":"text","text":" "},{"kind":"identifier","text":"pktSentNAK"},{"kind":"text","text":": "},{"kind":"typeIdentifier","preciseIdentifier":"s:s5Int32V","text":"Int32"}],"kind":"symbol"},"doc://SRTHaishinKit/documentation/SRTHaishinKit/SRTPerformanceData/byteAvailRcvBuf":{"abstract":[{"text":"The available UDT receiver buffer size","type":"text"}],"identifier":"doc:\/\/SRTHaishinKit\/documentation\/SRTHaishinKit\/SRTPerformanceData\/byteAvailRcvBuf","role":"symbol","type":"topic","title":"byteAvailRcvBuf","fragments":[{"kind":"keyword","text":"let"},{"kind":"text","text":" "},{"kind":"identifier","text":"byteAvailRcvBuf"},{"kind":"text","text":": "},{"preciseIdentifier":"s:s5Int32V","kind":"typeIdentifier","text":"Int32"}],"url":"\/documentation\/srthaishinkit\/srtperformancedata\/byteavailrcvbuf","kind":"symbol"},"doc://SRTHaishinKit/documentation/SRTHaishinKit/SRTPerformanceData/pktRcvUndecryptTotal":{"title":"pktRcvUndecryptTotal","fragments":[{"text":"let","kind":"keyword"},{"text":" ","kind":"text"},{"text":"pktRcvUndecryptTotal","kind":"identifier"},{"text":": ","kind":"text"},{"text":"Int32","kind":"typeIdentifier","preciseIdentifier":"s:s5Int32V"}],"role":"symbol","type":"topic","kind":"symbol","abstract":[{"type":"text","text":"The number of undecrypted packets"}],"url":"\/documentation\/srthaishinkit\/srtperformancedata\/pktrcvundecrypttotal","identifier":"doc:\/\/SRTHaishinKit\/documentation\/SRTHaishinKit\/SRTPerformanceData\/pktRcvUndecryptTotal"},"doc://SRTHaishinKit/documentation/SRTHaishinKit/SRTPerformanceData/pktReorderTolerance":{"role":"symbol","title":"pktReorderTolerance","identifier":"doc:\/\/SRTHaishinKit\/documentation\/SRTHaishinKit\/SRTPerformanceData\/pktReorderTolerance","abstract":[{"text":"The packet reorder tolerance value","type":"text"}],"url":"\/documentation\/srthaishinkit\/srtperformancedata\/pktreordertolerance","kind":"symbol","type":"topic","fragments":[{"text":"let","kind":"keyword"},{"text":" ","kind":"text"},{"text":"pktReorderTolerance","kind":"identifier"},{"text":": ","kind":"text"},{"text":"Int32","kind":"typeIdentifier","preciseIdentifier":"s:s5Int32V"}]},"doc://SRTHaishinKit/documentation/SRTHaishinKit/SRTPerformanceData/byteSndDropTotal":{"abstract":[{"type":"text","text":"The number of too-late-to-send dropped bytes"}],"url":"\/documentation\/srthaishinkit\/srtperformancedata\/bytesnddroptotal","title":"byteSndDropTotal","identifier":"doc:\/\/SRTHaishinKit\/documentation\/SRTHaishinKit\/SRTPerformanceData\/byteSndDropTotal","kind":"symbol","role":"symbol","fragments":[{"text":"let","kind":"keyword"},{"text":" ","kind":"text"},{"text":"byteSndDropTotal","kind":"identifier"},{"text":": ","kind":"text"},{"text":"UInt64","kind":"typeIdentifier","preciseIdentifier":"s:s6UInt64V"}],"type":"topic"},"doc://SRTHaishinKit/documentation/SRTHaishinKit/SRTPerformanceData/pktSndLossTotal":{"identifier":"doc:\/\/SRTHaishinKit\/documentation\/SRTHaishinKit\/SRTPerformanceData\/pktSndLossTotal","kind":"symbol","url":"\/documentation\/srthaishinkit\/srtperformancedata\/pktsndlosstotal","fragments":[{"kind":"keyword","text":"let"},{"kind":"text","text":" "},{"kind":"identifier","text":"pktSndLossTotal"},{"kind":"text","text":": "},{"preciseIdentifier":"s:s5Int32V","kind":"typeIdentifier","text":"Int32"}],"type":"topic","title":"pktSndLossTotal","role":"symbol","abstract":[{"type":"text","text":"The total number of lost packets (sender side)"}]}}}